.coveragerc
CHANGES.rst
COPYRIGHT.txt
HACKING.rst
LICENSE.txt
MANIFEST.in
Makefile
README.rst
bootstrap.py
buildout.cfg
setup.py
src/gocept/__init__.py
src/gocept.jsform.egg-info/PKG-INFO
src/gocept.jsform.egg-info/SOURCES.txt
src/gocept.jsform.egg-info/dependency_links.txt
src/gocept.jsform.egg-info/entry_points.txt
src/gocept.jsform.egg-info/namespace_packages.txt
src/gocept.jsform.egg-info/not-zip-safe
src/gocept.jsform.egg-info/requires.txt
src/gocept.jsform.egg-info/top_level.txt
src/gocept/jsform/__init__.py
src/gocept/jsform/resource.py
src/gocept/jsform/additional/handlebars-v4.0.2.js
src/gocept/jsform/additional/handlebars-v4.0.2.min.js
src/gocept/jsform/additional/ko.mapping.js
src/gocept/jsform/additional/ko.mapping.min.js
src/gocept/jsform/resources/bower.json
src/gocept/jsform/resources/collection.js
src/gocept/jsform/resources/collection.min.js
src/gocept/jsform/resources/helpers.js
src/gocept/jsform/resources/helpers.min.js
src/gocept/jsform/resources/jsform.js
src/gocept/jsform/resources/jsform.min.js
src/gocept/jsform/resources/template.js
src/gocept/jsform/resources/template.min.js
src/gocept/jsform/resources/templates.js
src/gocept/jsform/resources/templates.min.js
src/gocept/jsform/resources/localizations/de.js
src/gocept/jsform/resources/localizations/de.min.js
src/gocept/jsform/resources/localizations/en.js
src/gocept/jsform/resources/localizations/en.min.js
src/gocept/jsform/tests/__init__.py
src/gocept/jsform/tests/test_integration.py
src/gocept/jsform/tests/test_minification.py
src/gocept/jsform/tests/resources/groupwidget.js
src/gocept/jsform/tests/resources/jsform.js
src/gocept/jsform/tests/resources/listwidget.js
src/gocept/jsform/tests/resources/tablewidget.js
src/gocept/jsform/tests/resources/testdata.json
versions/versions.cfg
versions/ztk-versions-1.1.5.cfg