Metadata-Version: 2.1
Name: gocept.jsform
Version: 3.0.3
Summary: Next generation forms in javascript
Home-page: https://github.com/gocept/gocept.jsform
Author: Sebastian Wehrmann <sw@gocept.com>, Maik Derstappen <md@derico.de>
Author-email: sw@gocept.com
License: MIT
Keywords: form javascript jquery client
Platform: UNKNOWN
Classifier: Development Status :: 7 - Inactive
Classifier: License :: OSI Approved :: MIT License
Classifier: Programming Language :: Python
Classifier: Programming Language :: Python :: 2
Classifier: Programming Language :: Python :: 2.6
Classifier: Programming Language :: Python :: 2.7
Classifier: Programming Language :: Python :: 2 :: Only
Provides-Extra: listwidget
Provides-Extra: test
